flet_camera/__init__.py
flet_camera/camera_webview.py
flet_camera/assets/camera.html
flet_camera_webview-0.1.4.dist-info/METADATA
flet_camera_webview-0.1.4.dist-info/WHEEL
flet_camera_webview-0.1.4.dist-info/top_level.txt
flet_camera_webview-0.1.4.dist-info/RECORD
